sane_settings/__init__.py
sane_settings/configbase.py
sane_settings/exceptions.py
sane_settings/fields.py
sane_settings/models.py
sane_settings/py.typed
sane_settings-0.2.9.dist-info/METADATA
sane_settings-0.2.9.dist-info/WHEEL
sane_settings-0.2.9.dist-info/RECORD
