Metadata-Version: 2.4
Name: sane-settings
Version: 0.2.9
Summary: Add your description here
Author-email: Nicolas Paris <ni.paris@gmail.com>
Requires-Python: >=3.10
Requires-Dist: loguru
